{
    "desc": "<p>Abstract implementation of a list.<\/p>\n<p><code>ListBase<\/code> can be used as a base class for implementing the <code>List<\/code>\ninterface.<\/p>\n<p>All operations are defined in terms of <code>length<\/code>, <code>operator[]<\/code>,\n<code>operator[]=<\/code> and <code>length=<\/code>, which need to be implemented.<\/p>\n<p><em>NOTICE<\/em>: Forwarding just these four operations to a normal growable <a href=\"dart-core\/List-class.html\">List<\/a>\n(as created by <code>new List()<\/code>) will give very bad performance for <code>add<\/code> and\n<code>addAll<\/code> operations of <code>ListBase<\/code>. These operations are implemented by\nincreasing the length of the list by one for each <code>add<\/code> operation, and\nrepeatedly increasing the length of a growable list is not efficient.\nTo avoid this, either override 'add' and 'addAll' to also forward directly\nto the growable list, or, preferably, use <code>DelegatingList<\/code> from\n\"package:collection\/wrappers.dart\" instead.<\/p>\n    ",
    "dtype": "class",
    "example": "",
    "href": "dart-collection\/ListBase-class.html",
    "isAbstract": true,
    "isConstant": "0",
    "isDeprecated": false,
    "is_enum": 1,
    "is_mixin": 1,
    "is_typedef": 1,
    "memberOf": "dart:collection",
    "name": "dart:collection.ListBase",
    "shortname": "ListBase",
    "extends": [],
    "realImplementors": [
        "collection.CombinedListView",
        "dart:collection.UnmodifiableListView",
        "dart:typed_data.UnmodifiableFloat32ListView",
        "dart:typed_data.UnmodifiableFloat32x4ListView",
        "dart:typed_data.UnmodifiableFloat64ListView",
        "dart:typed_data.UnmodifiableFloat64x2ListView",
        "dart:typed_data.UnmodifiableInt16ListView",
        "dart:typed_data.UnmodifiableInt32ListView",
        "dart:typed_data.UnmodifiableInt32x4ListView",
        "dart:typed_data.UnmodifiableInt64ListView",
        "dart:typed_data.UnmodifiableInt8ListView",
        "dart:typed_data.UnmodifiableUint16ListView",
        "dart:typed_data.UnmodifiableUint32ListView",
        "dart:typed_data.UnmodifiableUint64ListView",
        "dart:typed_data.UnmodifiableUint8ClampedListView",
        "dart:typed_data.UnmodifiableUint8ListView",
        "typed_data.typed_buffers.Float32Buffer",
        "typed_data.typed_buffers.Float32x4Buffer",
        "typed_data.typed_buffers.Float64Buffer",
        "typed_data.typed_buffers.Int16Buffer",
        "typed_data.typed_buffers.Int32Buffer",
        "typed_data.typed_buffers.Int32x4Buffer",
        "typed_data.typed_buffers.Int64Buffer",
        "typed_data.typed_buffers.Int8Buffer",
        "typed_data.typed_buffers.Uint16Buffer",
        "typed_data.typed_buffers.Uint32Buffer",
        "typed_data.typed_buffers.Uint64Buffer",
        "typed_data.typed_buffers.Uint8Buffer",
        "typed_data.typed_buffers.Uint8ClampedBuffer"
    ],
    "events": [],
    "methods": [
        {
            "desc": null,
            "example": "",
            "href": "dart-collection\/ListBase\/ListBase.html",
            "isDeprecated": false,
            "type": "",
            "name": "ListBase",
            "dtype": "constructor",
            "isConstructor": true,
            "static": false,
            "memberOf": "dart:collection.ListBase",
            "params": []
        },
        {
            "desc": "<p>Convert a <code>List<\/code> to a string as <code>[each, element, as, string]<\/code>.<\/p>\n<p>Handles circular references where converting one of the elements\nto a string ends up converting <code>list<\/code> to a string again.<\/p>\n    ",
            "example": "<h2><span>Implementation<\/span><\/h2>\n      <pre class=\"language-dart\"><code class=\"language-dart\">static String listToString(List list) =&gt;\n    IterableBase.iterableToFullString(list, '[', ']');<\/code><\/pre>\n    ",
            "href": "dart-collection\/ListBase\/listToString.html",
            "isDeprecated": false,
            "type": "dart:core.String",
            "name": "listToString",
            "dtype": "method",
            "isConstructor": false,
            "static": false,
            "memberOf": "dart:collection.ListBase",
            "params": [
                {
                    "name": "list",
                    "desc": null,
                    "example": "",
                    "href": "",
                    "isDeprecated": false,
                    "isOptional": false,
                    "type": "dart:core.List"
                }
            ]
        }
    ],
    "props": []
}