{
    "desc": "<p>A fixed-length list of Int32x4 numbers that is viewable as a\n<a href=\"dart-typed_data\/TypedData-class.html\">TypedData<\/a>.<\/p>\n<p>For long lists, this implementation will be considerably more\nspace- and time-efficient than the default <a href=\"dart-core\/List-class.html\">List<\/a> implementation.<\/p>\n    ",
    "dtype": "class",
    "example": "",
    "href": "dart-typed_data\/Int32x4List-class.html",
    "isAbstract": true,
    "isConstant": "0",
    "isDeprecated": false,
    "is_enum": 1,
    "is_mixin": 1,
    "is_typedef": 1,
    "memberOf": "dart:typed_data",
    "name": "dart:typed_data.Int32x4List",
    "shortname": "Int32x4List",
    "extends": [],
    "realImplementors": [],
    "events": [],
    "methods": [
        {
            "desc": "<p>Creates a <a href=\"dart-typed_data\/Int32x4List-class.html\">Int32x4List<\/a> of the specified length (in elements),\nall of whose elements are initially zero.<\/p>\n    ",
            "example": "<h2><span>Implementation<\/span><\/h2>\n      <pre class=\"language-dart\"><code class=\"language-dart\">external factory Int32x4List(int length);<\/code><\/pre>\n    ",
            "href": "dart-typed_data\/Int32x4List\/Int32x4List.html",
            "isDeprecated": false,
            "type": "",
            "name": "Int32x4List",
            "dtype": "constructor",
            "isConstructor": true,
            "static": false,
            "memberOf": "dart:typed_data.Int32x4List",
            "params": [
                {
                    "name": "length",
                    "desc": "",
                    "example": "",
                    "href": "",
                    "isDeprecated": false,
                    "isOptional": true,
                    "type": "dart:core.int"
                }
            ]
        }
    ],
    "props": [
        {
            "desc": "",
            "example": "<h2><span>Implementation<\/span><\/h2>\n      <pre class=\"language-dart\"><code class=\"language-dart\">static const int bytesPerElement = 16\n\n<\/code><\/pre>\n    ",
            "href": "dart-typed_data\/Int32x4List\/bytesPerElement-constant.html",
            "name": "bytesPerElement",
            "isDeprecated": false,
            "type": "dart:core.int",
            "dtype": "constant",
            "isStatic": true,
            "isConstant": true,
            "memberOf": "dart:typed_data.Int32x4List",
            "params": []
        }
    ]
}