{
    "desc": "<p>The kind of <code>PointerDeviceKind.signal<\/code>.<\/p>\n    ",
    "dtype": "enum",
    "example": "",
    "href": "dart-ui\/PointerSignalKind-class.html",
    "isAbstract": false,
    "isConstant": false,
    "isDeprecated": false,
    "memberOf": "dart:ui",
    "name": "dart:ui.PointerSignalKind",
    "shortname": "PointerSignalKind",
    "extends": [],
    "is_enum": true,
    "is_mixin": false,
    "realImplementors": [],
    "events": [],
    "methods": [],
    "props": [
        {
            "desc": "\n          <p>The event is not associated with a pointer signal.<\/p>\n                  \n  <div>\n            <span class=\"signature\"><code>const PointerSignalKind(0)<\/code><\/span>\n          <\/div>\n        ",
            "example": "",
            "href": "",
            "name": "none",
            "isDeprecated": false,
            "type": "",
            "dtype": "enum-value",
            "isStatic": true,
            "isConstant": true,
            "memberOf": "dart:ui.PointerSignalKind",
            "params": []
        },
        {
            "desc": "\n          <p>A pointer-generated scroll (e.g., mouse wheel or trackpad scroll).<\/p>\n                  \n  <div>\n            <span class=\"signature\"><code>const PointerSignalKind(1)<\/code><\/span>\n          <\/div>\n        ",
            "example": "",
            "href": "",
            "name": "scroll",
            "isDeprecated": false,
            "type": "",
            "dtype": "enum-value",
            "isStatic": true,
            "isConstant": true,
            "memberOf": "dart:ui.PointerSignalKind",
            "params": []
        },
        {
            "desc": "\n          <p>An unknown pointer signal kind.<\/p>\n                  \n  <div>\n            <span class=\"signature\"><code>const PointerSignalKind(2)<\/code><\/span>\n          <\/div>\n        ",
            "example": "",
            "href": "",
            "name": "unknown",
            "isDeprecated": false,
            "type": "",
            "dtype": "enum-value",
            "isStatic": true,
            "isConstant": true,
            "memberOf": "dart:ui.PointerSignalKind",
            "params": []
        },
        {
            "desc": "\n          <p>A constant List of the values in this enum, in order of their declaration.<\/p>\n                  \n  <div>\n            <span class=\"signature\"><code>const List&lt;<wbr><span class=\"type-parameter\">PointerSignalKind<\/span>&gt;<\/wbr><\/code><\/span>\n          <\/div>\n        ",
            "example": "",
            "href": "",
            "name": "values",
            "isDeprecated": false,
            "type": "",
            "dtype": "enum-value",
            "isStatic": true,
            "isConstant": true,
            "memberOf": "dart:ui.PointerSignalKind",
            "params": []
        }
    ]
}