{
    "name": "dart:collection.UnmodifiableMapView",
    "extends": [
        "dart:collection.MapView",
        "dart:core.Object"
    ],
    "memberOf": "dart:collection",
    "events": [],
    "methods": [
        {
            "name": "UnmodifiableMapView",
            "type": "",
            "desc": "",
            "static": false,
            "memberOf": "dart:collection.UnmodifiableMapView",
            "sig": "",
            "params": [
                {
                    "name": "map",
                    "type": "dart:core.Map",
                    "desc": "",
                    "isOptional": true,
                    "href": "",
                    "example": "",
                    "isDeprecated": false
                }
            ],
            "isConstructor": true,
            "href": "dart-collection\/UnmodifiableMapView\/UnmodifiableMapView.html",
            "example": "<h2><span>Implementation<\/span><\/h2>\n      <pre class=\"language-dart\"><code class=\"language-dart\">UnmodifiableMapView(Map&lt;K, V&gt; map) : super(map);<\/code><\/pre>\n    ",
            "isDeprecated": false
        },
        {
            "name": "operator []=",
            "type": "",
            "desc": "<p>This operation is not supported by an unmodifiable map.<\/p>\n    ",
            "static": false,
            "memberOf": "dart:collection.UnmodifiableMapView",
            "sig": "",
            "params": [
                {
                    "name": "key",
                    "type": "",
                    "desc": "",
                    "isOptional": true,
                    "href": "",
                    "example": "",
                    "isDeprecated": false,
                    "types": []
                },
                {
                    "name": "value",
                    "type": "",
                    "desc": "",
                    "isOptional": true,
                    "href": "",
                    "example": "",
                    "isDeprecated": false,
                    "types": []
                }
            ],
            "isConstructor": false,
            "href": "dart-collection\/UnmodifiableMapView\/operator_put.html",
            "example": "<h2><span>Implementation<\/span><\/h2>\n      <pre class=\"language-dart\"><code class=\"language-dart\">void operator []=(K key, V value) {\n  throw UnsupportedError(\"Cannot modify unmodifiable map\");\n}<\/code><\/pre>\n    ",
            "isDeprecated": false,
            "types": []
        },
        {
            "name": "addAll",
            "type": "",
            "desc": "<p>This operation is not supported by an unmodifiable map.<\/p>\n    ",
            "static": false,
            "memberOf": "dart:collection.UnmodifiableMapView",
            "sig": "",
            "params": [
                {
                    "name": "other",
                    "type": "dart:core.Map",
                    "desc": "",
                    "isOptional": true,
                    "href": "",
                    "example": "",
                    "isDeprecated": false
                }
            ],
            "isConstructor": false,
            "href": "dart-collection\/UnmodifiableMapView\/addAll.html",
            "example": "<h2><span>Implementation<\/span><\/h2>\n      <pre class=\"language-dart\"><code class=\"language-dart\">void addAll(Map&lt;K, V&gt; other) {\n  throw UnsupportedError(\"Cannot modify unmodifiable map\");\n}<\/code><\/pre>\n    ",
            "isDeprecated": false,
            "types": []
        },
        {
            "name": "addEntries",
            "type": "",
            "desc": "<p>This operation is not supported by an unmodifiable map.<\/p>\n    ",
            "static": false,
            "memberOf": "dart:collection.UnmodifiableMapView",
            "sig": "",
            "params": [
                {
                    "name": "entries",
                    "type": "dart:core.Iterable<dart:core.MapEntry>",
                    "desc": "",
                    "isOptional": true,
                    "href": "",
                    "example": "",
                    "isDeprecated": false,
                    "types": [
                        "dart:core.Iterable",
                        "dart:core.MapEntry"
                    ]
                }
            ],
            "isConstructor": false,
            "href": "dart-collection\/UnmodifiableMapView\/addEntries.html",
            "example": "<h2><span>Implementation<\/span><\/h2>\n      <pre class=\"language-dart\"><code class=\"language-dart\">void addEntries(Iterable&lt;MapEntry&lt;K, V&gt;&gt; entries) {\n  throw UnsupportedError(\"Cannot modify unmodifiable map\");\n}<\/code><\/pre>\n    ",
            "isDeprecated": false,
            "types": []
        },
        {
            "name": "cast",
            "type": "dart:core.Map",
            "desc": "<p>Provides a view of this map as having <code>RK<\/code> keys and <code>RV<\/code> instances,\nif necessary.<\/p>\n<p>If this map is already a <code>Map&lt;RK, RV&gt;<\/code>, it is returned unchanged.<\/p>\n<p>If this set contains only keys of type <code>RK<\/code> and values of type <code>RV<\/code>,\nall read operations will work correctly.\nIf any operation exposes a non-<code>RK<\/code> key or non-<code>RV<\/code> value,\nthe operation will throw instead.<\/p>\n<p>Entries added to the map must be valid for both a <code>Map&lt;K, V&gt;<\/code> and a\n<code>Map&lt;RK, RV&gt;<\/code>.<\/p>\n    ",
            "static": false,
            "memberOf": "dart:collection.UnmodifiableMapView",
            "sig": "",
            "params": [],
            "isConstructor": false,
            "href": "dart-collection\/UnmodifiableMapView\/cast.html",
            "example": "<h2><span>Implementation<\/span><\/h2>\n      <pre class=\"language-dart\"><code class=\"language-dart\">Map&lt;RK, RV&gt; cast&lt;RK, RV&gt;() =&gt;\n    UnmodifiableMapView&lt;RK, RV&gt;(_map.cast&lt;RK, RV&gt;());<\/code><\/pre>\n    ",
            "isDeprecated": false
        },
        {
            "name": "clear",
            "type": "",
            "desc": "<p>This operation is not supported by an unmodifiable map.<\/p>\n    ",
            "static": false,
            "memberOf": "dart:collection.UnmodifiableMapView",
            "sig": "",
            "params": [],
            "isConstructor": false,
            "href": "dart-collection\/UnmodifiableMapView\/clear.html",
            "example": "<h2><span>Implementation<\/span><\/h2>\n      <pre class=\"language-dart\"><code class=\"language-dart\">void clear() {\n  throw UnsupportedError(\"Cannot modify unmodifiable map\");\n}<\/code><\/pre>\n    ",
            "isDeprecated": false,
            "types": []
        },
        {
            "name": "putIfAbsent",
            "type": "",
            "desc": "<p>This operation is not supported by an unmodifiable map.<\/p>\n    ",
            "static": false,
            "memberOf": "dart:collection.UnmodifiableMapView",
            "sig": "",
            "params": [
                {
                    "name": "key",
                    "type": "",
                    "desc": "",
                    "isOptional": true,
                    "href": "",
                    "example": "",
                    "isDeprecated": false,
                    "types": []
                },
                {
                    "name": "ifAbsent",
                    "type": "",
                    "desc": "",
                    "isOptional": true,
                    "href": "",
                    "example": "",
                    "isDeprecated": false,
                    "types": []
                }
            ],
            "isConstructor": false,
            "href": "dart-collection\/UnmodifiableMapView\/putIfAbsent.html",
            "example": "<h2><span>Implementation<\/span><\/h2>\n      <pre class=\"language-dart\"><code class=\"language-dart\">V putIfAbsent(K key, V ifAbsent()) {\n  throw UnsupportedError(\"Cannot modify unmodifiable map\");\n}<\/code><\/pre>\n    ",
            "isDeprecated": false,
            "types": []
        },
        {
            "name": "remove",
            "type": "",
            "desc": "<p>This operation is not supported by an unmodifiable map.<\/p>\n    ",
            "static": false,
            "memberOf": "dart:collection.UnmodifiableMapView",
            "sig": "",
            "params": [
                {
                    "name": "key",
                    "type": "dart:core.Object",
                    "desc": "",
                    "isOptional": true,
                    "href": "",
                    "example": "",
                    "isDeprecated": false
                }
            ],
            "isConstructor": false,
            "href": "dart-collection\/UnmodifiableMapView\/remove.html",
            "example": "<h2><span>Implementation<\/span><\/h2>\n      <pre class=\"language-dart\"><code class=\"language-dart\">V remove(Object key) {\n  throw UnsupportedError(\"Cannot modify unmodifiable map\");\n}<\/code><\/pre>\n    ",
            "isDeprecated": false,
            "types": []
        },
        {
            "name": "removeWhere",
            "type": "",
            "desc": "<p>This operation is not supported by an unmodifiable map.<\/p>\n    ",
            "static": false,
            "memberOf": "dart:collection.UnmodifiableMapView",
            "sig": "",
            "params": [
                {
                    "name": "value",
                    "type": "",
                    "desc": "",
                    "isOptional": true,
                    "href": "",
                    "example": "",
                    "isDeprecated": false,
                    "types": []
                },
                {
                    "name": "key",
                    "type": "",
                    "desc": "",
                    "isOptional": true,
                    "href": "",
                    "example": "",
                    "isDeprecated": false,
                    "types": []
                },
                {
                    "name": "value",
                    "type": "",
                    "desc": "",
                    "isOptional": true,
                    "href": "",
                    "example": "",
                    "isDeprecated": false,
                    "types": []
                }
            ],
            "isConstructor": false,
            "href": "dart-collection\/UnmodifiableMapView\/removeWhere.html",
            "example": "<h2><span>Implementation<\/span><\/h2>\n      <pre class=\"language-dart\"><code class=\"language-dart\">void removeWhere(bool test(K key, V value)) {\n  throw UnsupportedError(\"Cannot modify unmodifiable map\");\n}<\/code><\/pre>\n    ",
            "isDeprecated": false,
            "types": []
        },
        {
            "name": "update",
            "type": "",
            "desc": "<p>This operation is not supported by an unmodifiable map.<\/p>\n    ",
            "static": false,
            "memberOf": "dart:collection.UnmodifiableMapView",
            "sig": "",
            "params": [
                {
                    "name": "key",
                    "type": "",
                    "desc": "",
                    "isOptional": true,
                    "href": "",
                    "example": "",
                    "isDeprecated": false,
                    "types": []
                },
                {
                    "name": "value",
                    "type": "",
                    "desc": "",
                    "isOptional": true,
                    "href": "",
                    "example": "",
                    "isDeprecated": false,
                    "types": []
                },
                {
                    "name": "value",
                    "type": "",
                    "desc": "",
                    "isOptional": true,
                    "href": "",
                    "example": "",
                    "isDeprecated": false,
                    "types": []
                },
                {
                    "name": "ifAbsent",
                    "type": "",
                    "desc": "",
                    "isOptional": true,
                    "href": "",
                    "example": "",
                    "isDeprecated": false,
                    "types": []
                }
            ],
            "isConstructor": false,
            "href": "dart-collection\/UnmodifiableMapView\/update.html",
            "example": "<h2><span>Implementation<\/span><\/h2>\n      <pre class=\"language-dart\"><code class=\"language-dart\">V update(K key, V update(V value), {V ifAbsent()}) {\n  throw UnsupportedError(\"Cannot modify unmodifiable map\");\n}<\/code><\/pre>\n    ",
            "isDeprecated": false,
            "types": []
        },
        {
            "name": "updateAll",
            "type": "",
            "desc": "<p>This operation is not supported by an unmodifiable map.<\/p>\n    ",
            "static": false,
            "memberOf": "dart:collection.UnmodifiableMapView",
            "sig": "",
            "params": [
                {
                    "name": "value",
                    "type": "",
                    "desc": "",
                    "isOptional": true,
                    "href": "",
                    "example": "",
                    "isDeprecated": false,
                    "types": []
                },
                {
                    "name": "key",
                    "type": "",
                    "desc": "",
                    "isOptional": true,
                    "href": "",
                    "example": "",
                    "isDeprecated": false,
                    "types": []
                },
                {
                    "name": "value",
                    "type": "",
                    "desc": "",
                    "isOptional": true,
                    "href": "",
                    "example": "",
                    "isDeprecated": false,
                    "types": []
                }
            ],
            "isConstructor": false,
            "href": "dart-collection\/UnmodifiableMapView\/updateAll.html",
            "example": "<h2><span>Implementation<\/span><\/h2>\n      <pre class=\"language-dart\"><code class=\"language-dart\">void updateAll(V update(K key, V value)) {\n  throw UnsupportedError(\"Cannot modify unmodifiable map\");\n}<\/code><\/pre>\n    ",
            "isDeprecated": false,
            "types": []
        }
    ],
    "props": [],
    "isMixin": false,
    "isEnum": false,
    "isTypedef": false,
    "isConstant": false,
    "isAbstract": false,
    "implementors": [],
    "realImplementors": [],
    "cn": [],
    "href": "dart-collection\/UnmodifiableMapView-class.html",
    "desc": "<p>View of a <a href=\"dart-core\/Map-class.html\">Map<\/a> that disallow modifying the map.<\/p>\n<p>A wrapper around a <code>Map<\/code> that forwards all members to the map provided in\nthe constructor, except for operations that modify the map.\nModifying operations throw instead.<\/p>\n    ",
    "example": "",
    "isDeprecated": false,
    "dtype": "class",
    "shortname": "UnmodifiableMapView"
}