{
    "desc": "<p>The translations for Marathi (<code>mr<\/code>).<\/p>\n    ",
    "dtype": "class",
    "example": "",
    "href": "flutter_localizations\/MaterialLocalizationMr-class.html",
    "isAbstract": "0",
    "isConstant": "0",
    "isDeprecated": "0",
    "is_enum": 1,
    "is_mixin": 1,
    "is_typedef": 1,
    "memberOf": "flutter_localizations",
    "name": "flutter_localizations.MaterialLocalizationMr",
    "shortname": "MaterialLocalizationMr",
    "extends": [
        "flutter_localizations.GlobalMaterialLocalizations",
        "dart:core.Object"
    ],
    "realImplementors": [],
    "events": [],
    "methods": [
        {
            "desc": "<p>Create an instance of the translation bundle for Marathi.<\/p>\n<p>For details on the meaning of the arguments, see <a href=\"flutter_localizations\/GlobalMaterialLocalizations-class.html\">GlobalMaterialLocalizations<\/a>.<\/p>\n    ",
            "example": "<h2><span>Implementation<\/span><\/h2>\n      <pre class=\"language-dart\"><code class=\"language-dart\">const MaterialLocalizationMr({\n  String localeName = 'mr',\n  @required intl.DateFormat fullYearFormat,\n  @required intl.DateFormat mediumDateFormat,\n  @required intl.DateFormat longDateFormat,\n  @required intl.DateFormat yearMonthFormat,\n  @required intl.NumberFormat decimalFormat,\n  @required intl.NumberFormat twoDigitZeroPaddedFormat,\n}) : super(\n  localeName: localeName,\n  fullYearFormat: fullYearFormat,\n  mediumDateFormat: mediumDateFormat,\n  longDateFormat: longDateFormat,\n  yearMonthFormat: yearMonthFormat,\n  decimalFormat: decimalFormat,\n  twoDigitZeroPaddedFormat: twoDigitZeroPaddedFormat,\n);<\/code><\/pre>\n    ",
            "href": "flutter_localizations\/MaterialLocalizationMr\/MaterialLocalizationMr.html",
            "isDeprecated": "0",
            "type": "",
            "dtype": "constructor",
            "isConstructor": true,
            "static": false,
            "memberOf": "flutter_localizations.MaterialLocalizationMr",
            "params": [
                {
                    "name": "decimalFormat",
                    "desc": null,
                    "example": "",
                    "href": "",
                    "isDeprecated": "0",
                    "isOptional": true,
                    "type": "intl.NumberFormat"
                },
                {
                    "name": "fullYearFormat",
                    "desc": null,
                    "example": "",
                    "href": "",
                    "isDeprecated": "0",
                    "isOptional": true,
                    "type": "intl.DateFormat"
                },
                {
                    "name": "localeName",
                    "desc": null,
                    "example": "",
                    "href": "",
                    "isDeprecated": "0",
                    "isOptional": true,
                    "type": "dart:core.String"
                },
                {
                    "name": "longDateFormat",
                    "desc": null,
                    "example": "",
                    "href": "",
                    "isDeprecated": "0",
                    "isOptional": true,
                    "type": "intl.DateFormat"
                },
                {
                    "name": "mediumDateFormat",
                    "desc": null,
                    "example": "",
                    "href": "",
                    "isDeprecated": "0",
                    "isOptional": true,
                    "type": "intl.DateFormat"
                },
                {
                    "name": "twoDigitZeroPaddedFormat",
                    "desc": null,
                    "example": "",
                    "href": "",
                    "isDeprecated": "0",
                    "isOptional": true,
                    "type": "intl.NumberFormat"
                },
                {
                    "name": "yearMonthFormat",
                    "desc": null,
                    "example": "",
                    "href": "",
                    "isDeprecated": "0",
                    "isOptional": true,
                    "type": "intl.DateFormat"
                }
            ]
        }
    ],
    "props": [
        {
            "desc": "<p>The raw version of <a href=\"flutter_localizations\/GlobalMaterialLocalizations\/aboutListTileTitle.html\">aboutListTileTitle<\/a>, with <code>$applicationName<\/code> verbatim\nin the string.<\/p>\n        ",
            "example": "<h2><span>Implementation<\/span><\/h2>\n          <pre class=\"language-dart\"><code class=\"language-dart\">@override\nString get aboutListTileTitleRaw =&gt; r'$applicationName \u092c\u0926\u094d\u0926\u0932';<\/code><\/pre>\n        ",
            "href": "flutter_localizations\/MaterialLocalizationMr\/aboutListTileTitleRaw.html",
            "isDeprecated": "0",
            "type": "dart:core.String",
            "memberOf": "flutter_localizations.MaterialLocalizationMr",
            "params": []
        },
        {
            "desc": "<p>Label read out by accessibility tools (TalkBack or VoiceOver) when an\nalert dialog widget is opened.<\/p>\n        ",
            "example": "<h2><span>Implementation<\/span><\/h2>\n          <pre class=\"language-dart\"><code class=\"language-dart\">@override\nString get alertDialogLabel =&gt; r'\u0938\u0942\u091a\u0928\u093e';<\/code><\/pre>\n        ",
            "href": "flutter_localizations\/MaterialLocalizationMr\/alertDialogLabel.html",
            "isDeprecated": "0",
            "type": "dart:core.String",
            "memberOf": "flutter_localizations.MaterialLocalizationMr",
            "params": []
        },
        {
            "desc": "<p>The abbreviation for ante meridiem (before noon) shown in the time picker.<\/p>\n        ",
            "example": "<h2><span>Implementation<\/span><\/h2>\n          <pre class=\"language-dart\"><code class=\"language-dart\">@override\nString get anteMeridiemAbbreviation =&gt; r'AM';<\/code><\/pre>\n        ",
            "href": "flutter_localizations\/MaterialLocalizationMr\/anteMeridiemAbbreviation.html",
            "isDeprecated": "0",
            "type": "dart:core.String",
            "memberOf": "flutter_localizations.MaterialLocalizationMr",
            "params": []
        },
        {
            "desc": "<p>The <a href=\"material\/BackButton-class.html\">BackButton<\/a>'s tooltip.<\/p>\n        ",
            "example": "<h2><span>Implementation<\/span><\/h2>\n          <pre class=\"language-dart\"><code class=\"language-dart\">@override\nString get backButtonTooltip =&gt; r'\u092e\u093e\u0917\u0947';<\/code><\/pre>\n        ",
            "href": "flutter_localizations\/MaterialLocalizationMr\/backButtonTooltip.html",
            "isDeprecated": "0",
            "type": "dart:core.String",
            "memberOf": "flutter_localizations.MaterialLocalizationMr",
            "params": []
        },
        {
            "desc": "<p>Label for \"cancel\" buttons and menu items.<\/p>\n        ",
            "example": "<h2><span>Implementation<\/span><\/h2>\n          <pre class=\"language-dart\"><code class=\"language-dart\">@override\nString get cancelButtonLabel =&gt; r'\u0930\u0926\u094d\u0926 \u0915\u0930\u093e';<\/code><\/pre>\n        ",
            "href": "flutter_localizations\/MaterialLocalizationMr\/cancelButtonLabel.html",
            "isDeprecated": "0",
            "type": "dart:core.String",
            "memberOf": "flutter_localizations.MaterialLocalizationMr",
            "params": []
        },
        {
            "desc": "<p>Label for \"close\" buttons and menu items.<\/p>\n        ",
            "example": "<h2><span>Implementation<\/span><\/h2>\n          <pre class=\"language-dart\"><code class=\"language-dart\">@override\nString get closeButtonLabel =&gt; r'\u092c\u0902\u0926 \u0915\u0930\u093e';<\/code><\/pre>\n        ",
            "href": "flutter_localizations\/MaterialLocalizationMr\/closeButtonLabel.html",
            "isDeprecated": "0",
            "type": "dart:core.String",
            "memberOf": "flutter_localizations.MaterialLocalizationMr",
            "params": []
        },
        {
            "desc": "<p>The <a href=\"material\/CloseButton-class.html\">CloseButton<\/a>'s tooltip.<\/p>\n        ",
            "example": "<h2><span>Implementation<\/span><\/h2>\n          <pre class=\"language-dart\"><code class=\"language-dart\">@override\nString get closeButtonTooltip =&gt; r'\u092c\u0902\u0926 \u0915\u0930\u093e';<\/code><\/pre>\n        ",
            "href": "flutter_localizations\/MaterialLocalizationMr\/closeButtonTooltip.html",
            "isDeprecated": "0",
            "type": "dart:core.String",
            "memberOf": "flutter_localizations.MaterialLocalizationMr",
            "params": []
        },
        {
            "desc": "<p>The semantics hint to describe the tap action on a collapsed <a href=\"material\/ExpandIcon-class.html\">ExpandIcon<\/a>.<\/p>\n        ",
            "example": "<h2><span>Implementation<\/span><\/h2>\n          <pre class=\"language-dart\"><code class=\"language-dart\">@override\nString get collapsedIconTapHint =&gt; r'\u0935\u093f\u0938\u094d\u0924\u093e\u0930 \u0915\u0930\u093e';<\/code><\/pre>\n        ",
            "href": "flutter_localizations\/MaterialLocalizationMr\/collapsedIconTapHint.html",
            "isDeprecated": "0",
            "type": "dart:core.String",
            "memberOf": "flutter_localizations.MaterialLocalizationMr",
            "params": []
        },
        {
            "desc": "<p>Label for \"continue\" buttons and menu items.<\/p>\n        ",
            "example": "<h2><span>Implementation<\/span><\/h2>\n          <pre class=\"language-dart\"><code class=\"language-dart\">@override\nString get continueButtonLabel =&gt; r'\u0938\u0941\u0930\u0942 \u0920\u0947\u0935\u093e';<\/code><\/pre>\n        ",
            "href": "flutter_localizations\/MaterialLocalizationMr\/continueButtonLabel.html",
            "isDeprecated": "0",
            "type": "dart:core.String",
            "memberOf": "flutter_localizations.MaterialLocalizationMr",
            "params": []
        },
        {
            "desc": "<p>Label for \"copy\" edit buttons and menu items.<\/p>\n        ",
            "example": "<h2><span>Implementation<\/span><\/h2>\n          <pre class=\"language-dart\"><code class=\"language-dart\">@override\nString get copyButtonLabel =&gt; r'\u0915\u0949\u092a\u0940 \u0915\u0930\u093e';<\/code><\/pre>\n        ",
            "href": "flutter_localizations\/MaterialLocalizationMr\/copyButtonLabel.html",
            "isDeprecated": "0",
            "type": "dart:core.String",
            "memberOf": "flutter_localizations.MaterialLocalizationMr",
            "params": []
        },
        {
            "desc": "<p>Label for \"cut\" edit buttons and menu items.<\/p>\n        ",
            "example": "<h2><span>Implementation<\/span><\/h2>\n          <pre class=\"language-dart\"><code class=\"language-dart\">@override\nString get cutButtonLabel =&gt; r'\u0915\u091f \u0915\u0930\u093e';<\/code><\/pre>\n        ",
            "href": "flutter_localizations\/MaterialLocalizationMr\/cutButtonLabel.html",
            "isDeprecated": "0",
            "type": "dart:core.String",
            "memberOf": "flutter_localizations.MaterialLocalizationMr",
            "params": []
        },
        {
            "desc": "<p>The tooltip for the delete button on a <a href=\"material\/Chip-class.html\">Chip<\/a>.<\/p>\n        ",
            "example": "<h2><span>Implementation<\/span><\/h2>\n          <pre class=\"language-dart\"><code class=\"language-dart\">@override\nString get deleteButtonTooltip =&gt; r'\u0939\u091f\u0935\u093e';<\/code><\/pre>\n        ",
            "href": "flutter_localizations\/MaterialLocalizationMr\/deleteButtonTooltip.html",
            "isDeprecated": "0",
            "type": "dart:core.String",
            "memberOf": "flutter_localizations.MaterialLocalizationMr",
            "params": []
        },
        {
            "desc": "<p>Label read out by accessibility tools (TalkBack or VoiceOver) when a\ndialog widget is opened.<\/p>\n        ",
            "example": "<h2><span>Implementation<\/span><\/h2>\n          <pre class=\"language-dart\"><code class=\"language-dart\">@override\nString get dialogLabel =&gt; r'\u0921\u093e\u092f\u0932\u0949\u0917';<\/code><\/pre>\n        ",
            "href": "flutter_localizations\/MaterialLocalizationMr\/dialogLabel.html",
            "isDeprecated": "0",
            "type": "dart:core.String",
            "memberOf": "flutter_localizations.MaterialLocalizationMr",
            "params": []
        },
        {
            "desc": "<p>Label read out by accessibility tools (TalkBack or VoiceOver) when a\ndrawer widget is opened.<\/p>\n        ",
            "example": "<h2><span>Implementation<\/span><\/h2>\n          <pre class=\"language-dart\"><code class=\"language-dart\">@override\nString get drawerLabel =&gt; r'\u0928\u0947\u0935\u094d\u0939\u093f\u0917\u0947\u0936\u0928 \u092e\u0947\u0928\u0942';<\/code><\/pre>\n        ",
            "href": "flutter_localizations\/MaterialLocalizationMr\/drawerLabel.html",
            "isDeprecated": "0",
            "type": "dart:core.String",
            "memberOf": "flutter_localizations.MaterialLocalizationMr",
            "params": []
        },
        {
            "desc": "<p>The semantics hint to describe the tap action on an expanded <a href=\"material\/ExpandIcon-class.html\">ExpandIcon<\/a>.<\/p>\n        ",
            "example": "<h2><span>Implementation<\/span><\/h2>\n          <pre class=\"language-dart\"><code class=\"language-dart\">@override\nString get expandedIconTapHint =&gt; r'\u0915\u094b\u0932\u0945\u092a\u094d\u0938 \u0915\u0930\u093e';<\/code><\/pre>\n        ",
            "href": "flutter_localizations\/MaterialLocalizationMr\/expandedIconTapHint.html",
            "isDeprecated": "0",
            "type": "dart:core.String",
            "memberOf": "flutter_localizations.MaterialLocalizationMr",
            "params": []
        },
        {
            "desc": "<p>The semantics label used for the button on <a href=\"material\/UserAccountsDrawerHeader-class.html\">UserAccountsDrawerHeader<\/a> that\nhides the list of accounts.<\/p>\n        ",
            "example": "<h2><span>Implementation<\/span><\/h2>\n          <pre class=\"language-dart\"><code class=\"language-dart\">@override\nString get hideAccountsLabel =&gt; r'\u0916\u093e\u0924\u0940 \u0932\u092a\u0935\u093e';<\/code><\/pre>\n        ",
            "href": "flutter_localizations\/MaterialLocalizationMr\/hideAccountsLabel.html",
            "isDeprecated": "0",
            "type": "dart:core.String",
            "memberOf": "flutter_localizations.MaterialLocalizationMr",
            "params": []
        },
        {
            "desc": "<p>Title for the <a href=\"material\/LicensePage-class.html\">LicensePage<\/a> widget.<\/p>\n        ",
            "example": "<h2><span>Implementation<\/span><\/h2>\n          <pre class=\"language-dart\"><code class=\"language-dart\">@override\nString get licensesPageTitle =&gt; r'\u092a\u0930\u0935\u093e\u0928\u0947';<\/code><\/pre>\n        ",
            "href": "flutter_localizations\/MaterialLocalizationMr\/licensesPageTitle.html",
            "isDeprecated": "0",
            "type": "dart:core.String",
            "memberOf": "flutter_localizations.MaterialLocalizationMr",
            "params": []
        },
        {
            "desc": "<p>Label read out by accessibility tools (TalkBack or VoiceOver) for a modal\nbarrier to indicate that a tap dismisses the barrier.<\/p>\n<p>A modal barrier can for example be found behind an alert or popup to block\nuser interaction with elements behind it.<\/p>\n        ",
            "example": "<h2><span>Implementation<\/span><\/h2>\n          <pre class=\"language-dart\"><code class=\"language-dart\">@override\nString get modalBarrierDismissLabel =&gt; r'\u0921\u093f\u0938\u092e\u093f\u0938 \u0915\u0930\u093e';<\/code><\/pre>\n        ",
            "href": "flutter_localizations\/MaterialLocalizationMr\/modalBarrierDismissLabel.html",
            "isDeprecated": "0",
            "type": "dart:core.String",
            "memberOf": "flutter_localizations.MaterialLocalizationMr",
            "params": []
        },
        {
            "desc": "<p>The tooltip for the <a href=\"material\/MonthPicker-class.html\">MonthPicker<\/a>'s \"next month\" button.<\/p>\n        ",
            "example": "<h2><span>Implementation<\/span><\/h2>\n          <pre class=\"language-dart\"><code class=\"language-dart\">@override\nString get nextMonthTooltip =&gt; r'\u092a\u0941\u0922\u0940\u0932 \u092e\u0939\u093f\u0928\u093e';<\/code><\/pre>\n        ",
            "href": "flutter_localizations\/MaterialLocalizationMr\/nextMonthTooltip.html",
            "isDeprecated": "0",
            "type": "dart:core.String",
            "memberOf": "flutter_localizations.MaterialLocalizationMr",
            "params": []
        },
        {
            "desc": "<p>The tooltip for the <a href=\"material\/PaginatedDataTable-class.html\">PaginatedDataTable<\/a>'s \"next page\" button.<\/p>\n        ",
            "example": "<h2><span>Implementation<\/span><\/h2>\n          <pre class=\"language-dart\"><code class=\"language-dart\">@override\nString get nextPageTooltip =&gt; r'\u092a\u0941\u0922\u0940\u0932 \u092a\u0947\u091c';<\/code><\/pre>\n        ",
            "href": "flutter_localizations\/MaterialLocalizationMr\/nextPageTooltip.html",
            "isDeprecated": "0",
            "type": "dart:core.String",
            "memberOf": "flutter_localizations.MaterialLocalizationMr",
            "params": []
        },
        {
            "desc": "<p>Label for OK buttons and menu items.<\/p>\n        ",
            "example": "<h2><span>Implementation<\/span><\/h2>\n          <pre class=\"language-dart\"><code class=\"language-dart\">@override\nString get okButtonLabel =&gt; r'\u0913\u0915\u0947';<\/code><\/pre>\n        ",
            "href": "flutter_localizations\/MaterialLocalizationMr\/okButtonLabel.html",
            "isDeprecated": "0",
            "type": "dart:core.String",
            "memberOf": "flutter_localizations.MaterialLocalizationMr",
            "params": []
        },
        {
            "desc": "<p>The tooltip for the leading <a href=\"material\/AppBar-class.html\">AppBar<\/a> menu (a.k.a. 'hamburger') button.<\/p>\n        ",
            "example": "<h2><span>Implementation<\/span><\/h2>\n          <pre class=\"language-dart\"><code class=\"language-dart\">@override\nString get openAppDrawerTooltip =&gt; r'\u0928\u0947\u0935\u094d\u0939\u093f\u0917\u0947\u0936\u0928 \u092e\u0947\u0928\u0942 \u0909\u0918\u0921\u093e';<\/code><\/pre>\n        ",
            "href": "flutter_localizations\/MaterialLocalizationMr\/openAppDrawerTooltip.html",
            "isDeprecated": "0",
            "type": "dart:core.String",
            "memberOf": "flutter_localizations.MaterialLocalizationMr",
            "params": []
        },
        {
            "desc": "<p>The raw version of <a href=\"flutter_localizations\/GlobalMaterialLocalizations\/pageRowsInfoTitle.html\">pageRowsInfoTitle<\/a>, with <code>$firstRow<\/code>, <code>$lastRow<\/code>' and\n<code>$rowCount<\/code> verbatim in the string, for the case where the value is\napproximate.<\/p>\n        ",
            "example": "<h2><span>Implementation<\/span><\/h2>\n          <pre class=\"language-dart\"><code class=\"language-dart\">@override\nString get pageRowsInfoTitleApproximateRaw =&gt; r'$rowCount \u091a\u094d\u092f\u093e \u092c\u0926\u094d\u0926\u0932 $firstRow\u2013$lastRow';<\/code><\/pre>\n        ",
            "href": "flutter_localizations\/MaterialLocalizationMr\/pageRowsInfoTitleApproximateRaw.html",
            "isDeprecated": "0",
            "type": "dart:core.String",
            "memberOf": "flutter_localizations.MaterialLocalizationMr",
            "params": []
        },
        {
            "desc": "<p>The raw version of <a href=\"flutter_localizations\/GlobalMaterialLocalizations\/pageRowsInfoTitle.html\">pageRowsInfoTitle<\/a>, with <code>$firstRow<\/code>, <code>$lastRow<\/code>' and\n<code>$rowCount<\/code> verbatim in the string, for the case where the value is\nprecise.<\/p>\n        ",
            "example": "<h2><span>Implementation<\/span><\/h2>\n          <pre class=\"language-dart\"><code class=\"language-dart\">@override\nString get pageRowsInfoTitleRaw =&gt; r'$rowCount \u092a\u0948\u0915\u0940 $firstRow\u2013$lastRow';<\/code><\/pre>\n        ",
            "href": "flutter_localizations\/MaterialLocalizationMr\/pageRowsInfoTitleRaw.html",
            "isDeprecated": "0",
            "type": "dart:core.String",
            "memberOf": "flutter_localizations.MaterialLocalizationMr",
            "params": []
        },
        {
            "desc": "<p>Label for \"paste\" edit buttons and menu items.<\/p>\n        ",
            "example": "<h2><span>Implementation<\/span><\/h2>\n          <pre class=\"language-dart\"><code class=\"language-dart\">@override\nString get pasteButtonLabel =&gt; r'\u092a\u0947\u0938\u094d\u091f \u0915\u0930\u093e';<\/code><\/pre>\n        ",
            "href": "flutter_localizations\/MaterialLocalizationMr\/pasteButtonLabel.html",
            "isDeprecated": "0",
            "type": "dart:core.String",
            "memberOf": "flutter_localizations.MaterialLocalizationMr",
            "params": []
        },
        {
            "desc": "<p>Label read out by accessibility tools (TalkBack or VoiceOver) when a\npopup menu widget is opened.<\/p>\n        ",
            "example": "<h2><span>Implementation<\/span><\/h2>\n          <pre class=\"language-dart\"><code class=\"language-dart\">@override\nString get popupMenuLabel =&gt; r'\u092a\u0949\u092a\u0905\u092a \u092e\u0947\u0928\u0942';<\/code><\/pre>\n        ",
            "href": "flutter_localizations\/MaterialLocalizationMr\/popupMenuLabel.html",
            "isDeprecated": "0",
            "type": "dart:core.String",
            "memberOf": "flutter_localizations.MaterialLocalizationMr",
            "params": []
        },
        {
            "desc": "<p>The abbreviation for post meridiem (after noon) shown in the time picker.<\/p>\n        ",
            "example": "<h2><span>Implementation<\/span><\/h2>\n          <pre class=\"language-dart\"><code class=\"language-dart\">@override\nString get postMeridiemAbbreviation =&gt; r'PM';<\/code><\/pre>\n        ",
            "href": "flutter_localizations\/MaterialLocalizationMr\/postMeridiemAbbreviation.html",
            "isDeprecated": "0",
            "type": "dart:core.String",
            "memberOf": "flutter_localizations.MaterialLocalizationMr",
            "params": []
        },
        {
            "desc": "<p>The tooltip for the <a href=\"material\/MonthPicker-class.html\">MonthPicker<\/a>'s \"previous month\" button.<\/p>\n        ",
            "example": "<h2><span>Implementation<\/span><\/h2>\n          <pre class=\"language-dart\"><code class=\"language-dart\">@override\nString get previousMonthTooltip =&gt; r'\u092e\u093e\u0917\u0940\u0932 \u092e\u0939\u093f\u0928\u093e';<\/code><\/pre>\n        ",
            "href": "flutter_localizations\/MaterialLocalizationMr\/previousMonthTooltip.html",
            "isDeprecated": "0",
            "type": "dart:core.String",
            "memberOf": "flutter_localizations.MaterialLocalizationMr",
            "params": []
        },
        {
            "desc": "<p>The tooltip for the <a href=\"material\/PaginatedDataTable-class.html\">PaginatedDataTable<\/a>'s \"previous page\" button.<\/p>\n        ",
            "example": "<h2><span>Implementation<\/span><\/h2>\n          <pre class=\"language-dart\"><code class=\"language-dart\">@override\nString get previousPageTooltip =&gt; r'\u092e\u093e\u0917\u0940\u0932 \u092a\u0947\u091c';<\/code><\/pre>\n        ",
            "href": "flutter_localizations\/MaterialLocalizationMr\/previousPageTooltip.html",
            "isDeprecated": "0",
            "type": "dart:core.String",
            "memberOf": "flutter_localizations.MaterialLocalizationMr",
            "params": []
        },
        {
            "desc": "<p>The default semantics label for a <a href=\"material\/RefreshIndicator-class.html\">RefreshIndicator<\/a>.<\/p>\n        ",
            "example": "<h2><span>Implementation<\/span><\/h2>\n          <pre class=\"language-dart\"><code class=\"language-dart\">@override\nString get refreshIndicatorSemanticLabel =&gt; r'\u0930\u093f\u092b\u094d\u0930\u0947\u0936 \u0915\u0930\u093e';<\/code><\/pre>\n        ",
            "href": "flutter_localizations\/MaterialLocalizationMr\/refreshIndicatorSemanticLabel.html",
            "isDeprecated": "0",
            "type": "dart:core.String",
            "memberOf": "flutter_localizations.MaterialLocalizationMr",
            "params": []
        },
        {
            "desc": "<p>The \"few\" form of <a href=\"flutter_localizations\/GlobalMaterialLocalizations\/remainingTextFieldCharacterCount.html\">remainingTextFieldCharacterCount<\/a>.<\/p>\n<p>This form is optional.<\/p>\n<p>See also:<\/p>\n<ul>\n<li>\n<a href=\"intl\/Intl\/plural.html\">Intl.plural<\/a>, to which this form is passed.<\/li>\n<li>\n<a href=\"flutter_localizations\/MaterialLocalizationMr\/remainingTextFieldCharacterCountZero.html\">remainingTextFieldCharacterCountZero<\/a>, the \"zero\" form<\/li>\n<li>\n<a href=\"flutter_localizations\/MaterialLocalizationMr\/remainingTextFieldCharacterCountOne.html\">remainingTextFieldCharacterCountOne<\/a>, the \"one\" form<\/li>\n<li>\n<a href=\"flutter_localizations\/MaterialLocalizationMr\/remainingTextFieldCharacterCountTwo.html\">remainingTextFieldCharacterCountTwo<\/a>, the \"two\" form<\/li>\n<li>\n<a href=\"flutter_localizations\/MaterialLocalizationMr\/remainingTextFieldCharacterCountFew.html\">remainingTextFieldCharacterCountFew<\/a>, the \"few\" form<\/li>\n<li>\n<a href=\"flutter_localizations\/MaterialLocalizationMr\/remainingTextFieldCharacterCountMany.html\">remainingTextFieldCharacterCountMany<\/a>, the \"many\" form<\/li>\n<li>\n<a href=\"flutter_localizations\/MaterialLocalizationMr\/remainingTextFieldCharacterCountOther.html\">remainingTextFieldCharacterCountOther<\/a>, the \"other\" form<\/li>\n<\/ul>",
            "example": "<h2><span>Implementation<\/span><\/h2>\n          <pre class=\"language-dart\"><code class=\"language-dart\">@override\nString get remainingTextFieldCharacterCountFew =&gt; null;<\/code><\/pre>\n        ",
            "href": "flutter_localizations\/MaterialLocalizationMr\/remainingTextFieldCharacterCountFew.html",
            "isDeprecated": "0",
            "type": "dart:core.String",
            "memberOf": "flutter_localizations.MaterialLocalizationMr",
            "params": []
        },
        {
            "desc": "<p>The \"many\" form of <a href=\"flutter_localizations\/GlobalMaterialLocalizations\/remainingTextFieldCharacterCount.html\">remainingTextFieldCharacterCount<\/a>.<\/p>\n<p>This form is optional.<\/p>\n<p>See also:<\/p>\n<ul>\n<li>\n<a href=\"intl\/Intl\/plural.html\">Intl.plural<\/a>, to which this form is passed.<\/li>\n<li>\n<a href=\"flutter_localizations\/MaterialLocalizationMr\/remainingTextFieldCharacterCountZero.html\">remainingTextFieldCharacterCountZero<\/a>, the \"zero\" form<\/li>\n<li>\n<a href=\"flutter_localizations\/MaterialLocalizationMr\/remainingTextFieldCharacterCountOne.html\">remainingTextFieldCharacterCountOne<\/a>, the \"one\" form<\/li>\n<li>\n<a href=\"flutter_localizations\/MaterialLocalizationMr\/remainingTextFieldCharacterCountTwo.html\">remainingTextFieldCharacterCountTwo<\/a>, the \"two\" form<\/li>\n<li>\n<a href=\"flutter_localizations\/MaterialLocalizationMr\/remainingTextFieldCharacterCountFew.html\">remainingTextFieldCharacterCountFew<\/a>, the \"few\" form<\/li>\n<li>\n<a href=\"flutter_localizations\/MaterialLocalizationMr\/remainingTextFieldCharacterCountMany.html\">remainingTextFieldCharacterCountMany<\/a>, the \"many\" form<\/li>\n<li>\n<a href=\"flutter_localizations\/MaterialLocalizationMr\/remainingTextFieldCharacterCountOther.html\">remainingTextFieldCharacterCountOther<\/a>, the \"other\" form<\/li>\n<\/ul>",
            "example": "<h2><span>Implementation<\/span><\/h2>\n          <pre class=\"language-dart\"><code class=\"language-dart\">@override\nString get remainingTextFieldCharacterCountMany =&gt; null;<\/code><\/pre>\n        ",
            "href": "flutter_localizations\/MaterialLocalizationMr\/remainingTextFieldCharacterCountMany.html",
            "isDeprecated": "0",
            "type": "dart:core.String",
            "memberOf": "flutter_localizations.MaterialLocalizationMr",
            "params": []
        },
        {
            "desc": "<p>The \"one\" form of <a href=\"flutter_localizations\/GlobalMaterialLocalizations\/remainingTextFieldCharacterCount.html\">remainingTextFieldCharacterCount<\/a>.<\/p>\n<p>This form is optional.<\/p>\n<p>See also:<\/p>\n<ul>\n<li>\n<a href=\"flutter_localizations\/MaterialLocalizationMr\/remainingTextFieldCharacterCountZero.html\">remainingTextFieldCharacterCountZero<\/a>, the \"zero\" form<\/li>\n<li>\n<a href=\"flutter_localizations\/MaterialLocalizationMr\/remainingTextFieldCharacterCountOne.html\">remainingTextFieldCharacterCountOne<\/a>, the \"one\" form<\/li>\n<li>\n<a href=\"flutter_localizations\/MaterialLocalizationMr\/remainingTextFieldCharacterCountTwo.html\">remainingTextFieldCharacterCountTwo<\/a>, the \"two\" form<\/li>\n<li>\n<a href=\"flutter_localizations\/MaterialLocalizationMr\/remainingTextFieldCharacterCountFew.html\">remainingTextFieldCharacterCountFew<\/a>, the \"few\" form<\/li>\n<li>\n<a href=\"flutter_localizations\/MaterialLocalizationMr\/remainingTextFieldCharacterCountMany.html\">remainingTextFieldCharacterCountMany<\/a>, the \"many\" form<\/li>\n<li>\n<a href=\"flutter_localizations\/MaterialLocalizationMr\/remainingTextFieldCharacterCountOther.html\">remainingTextFieldCharacterCountOther<\/a>, the \"other\" form<\/li>\n<\/ul>",
            "example": "<h2><span>Implementation<\/span><\/h2>\n          <pre class=\"language-dart\"><code class=\"language-dart\">@override\nString get remainingTextFieldCharacterCountOne =&gt; r'\u090f\u0915 \u0935\u0930\u094d\u0923 \u0936\u093f\u0932\u094d\u0932\u0915';<\/code><\/pre>\n        ",
            "href": "flutter_localizations\/MaterialLocalizationMr\/remainingTextFieldCharacterCountOne.html",
            "isDeprecated": "0",
            "type": "dart:core.String",
            "memberOf": "flutter_localizations.MaterialLocalizationMr",
            "params": []
        },
        {
            "desc": "<p>The \"other\" form of <a href=\"flutter_localizations\/GlobalMaterialLocalizations\/remainingTextFieldCharacterCount.html\">remainingTextFieldCharacterCount<\/a>.<\/p>\n<p>This form is required.<\/p>\n<p>See also:<\/p>\n<ul>\n<li>\n<a href=\"intl\/Intl\/plural.html\">Intl.plural<\/a>, to which this form is passed.<\/li>\n<li>\n<a href=\"flutter_localizations\/MaterialLocalizationMr\/remainingTextFieldCharacterCountZero.html\">remainingTextFieldCharacterCountZero<\/a>, the \"zero\" form<\/li>\n<li>\n<a href=\"flutter_localizations\/MaterialLocalizationMr\/remainingTextFieldCharacterCountOne.html\">remainingTextFieldCharacterCountOne<\/a>, the \"one\" form<\/li>\n<li>\n<a href=\"flutter_localizations\/MaterialLocalizationMr\/remainingTextFieldCharacterCountTwo.html\">remainingTextFieldCharacterCountTwo<\/a>, the \"two\" form<\/li>\n<li>\n<a href=\"flutter_localizations\/MaterialLocalizationMr\/remainingTextFieldCharacterCountFew.html\">remainingTextFieldCharacterCountFew<\/a>, the \"few\" form<\/li>\n<li>\n<a href=\"flutter_localizations\/MaterialLocalizationMr\/remainingTextFieldCharacterCountMany.html\">remainingTextFieldCharacterCountMany<\/a>, the \"many\" form<\/li>\n<li>\n<a href=\"flutter_localizations\/MaterialLocalizationMr\/remainingTextFieldCharacterCountOther.html\">remainingTextFieldCharacterCountOther<\/a>, the \"other\" form<\/li>\n<\/ul>",
            "example": "<h2><span>Implementation<\/span><\/h2>\n          <pre class=\"language-dart\"><code class=\"language-dart\">@override\nString get remainingTextFieldCharacterCountOther =&gt; r'$remainingCount \u0935\u0930\u094d\u0923 \u0936\u093f\u0932\u094d\u0932\u0915';<\/code><\/pre>\n        ",
            "href": "flutter_localizations\/MaterialLocalizationMr\/remainingTextFieldCharacterCountOther.html",
            "isDeprecated": "0",
            "type": "dart:core.String",
            "memberOf": "flutter_localizations.MaterialLocalizationMr",
            "params": []
        },
        {
            "desc": "<p>The \"two\" form of <a href=\"flutter_localizations\/GlobalMaterialLocalizations\/remainingTextFieldCharacterCount.html\">remainingTextFieldCharacterCount<\/a>.<\/p>\n<p>This form is optional.<\/p>\n<p>See also:<\/p>\n<ul>\n<li>\n<a href=\"intl\/Intl\/plural.html\">Intl.plural<\/a>, to which this form is passed.<\/li>\n<li>\n<a href=\"flutter_localizations\/MaterialLocalizationMr\/remainingTextFieldCharacterCountZero.html\">remainingTextFieldCharacterCountZero<\/a>, the \"zero\" form<\/li>\n<li>\n<a href=\"flutter_localizations\/MaterialLocalizationMr\/remainingTextFieldCharacterCountOne.html\">remainingTextFieldCharacterCountOne<\/a>, the \"one\" form<\/li>\n<li>\n<a href=\"flutter_localizations\/MaterialLocalizationMr\/remainingTextFieldCharacterCountTwo.html\">remainingTextFieldCharacterCountTwo<\/a>, the \"two\" form<\/li>\n<li>\n<a href=\"flutter_localizations\/MaterialLocalizationMr\/remainingTextFieldCharacterCountFew.html\">remainingTextFieldCharacterCountFew<\/a>, the \"few\" form<\/li>\n<li>\n<a href=\"flutter_localizations\/MaterialLocalizationMr\/remainingTextFieldCharacterCountMany.html\">remainingTextFieldCharacterCountMany<\/a>, the \"many\" form<\/li>\n<li>\n<a href=\"flutter_localizations\/MaterialLocalizationMr\/remainingTextFieldCharacterCountOther.html\">remainingTextFieldCharacterCountOther<\/a>, the \"other\" form<\/li>\n<\/ul>",
            "example": "<h2><span>Implementation<\/span><\/h2>\n          <pre class=\"language-dart\"><code class=\"language-dart\">@override\nString get remainingTextFieldCharacterCountTwo =&gt; null;<\/code><\/pre>\n        ",
            "href": "flutter_localizations\/MaterialLocalizationMr\/remainingTextFieldCharacterCountTwo.html",
            "isDeprecated": "0",
            "type": "dart:core.String",
            "memberOf": "flutter_localizations.MaterialLocalizationMr",
            "params": []
        },
        {
            "desc": "<p>The \"zero\" form of <a href=\"flutter_localizations\/GlobalMaterialLocalizations\/remainingTextFieldCharacterCount.html\">remainingTextFieldCharacterCount<\/a>.<\/p>\n<p>This form is required.<\/p>\n<p>See also:<\/p>\n<ul>\n<li>\n<a href=\"intl\/Intl\/plural.html\">Intl.plural<\/a>, to which this form is passed.<\/li>\n<li>\n<a href=\"flutter_localizations\/MaterialLocalizationMr\/remainingTextFieldCharacterCountZero.html\">remainingTextFieldCharacterCountZero<\/a>, the \"zero\" form<\/li>\n<li>\n<a href=\"flutter_localizations\/MaterialLocalizationMr\/remainingTextFieldCharacterCountOne.html\">remainingTextFieldCharacterCountOne<\/a>, the \"one\" form<\/li>\n<li>\n<a href=\"flutter_localizations\/MaterialLocalizationMr\/remainingTextFieldCharacterCountTwo.html\">remainingTextFieldCharacterCountTwo<\/a>, the \"two\" form<\/li>\n<li>\n<a href=\"flutter_localizations\/MaterialLocalizationMr\/remainingTextFieldCharacterCountFew.html\">remainingTextFieldCharacterCountFew<\/a>, the \"few\" form<\/li>\n<li>\n<a href=\"flutter_localizations\/MaterialLocalizationMr\/remainingTextFieldCharacterCountMany.html\">remainingTextFieldCharacterCountMany<\/a>, the \"many\" form<\/li>\n<li>\n<a href=\"flutter_localizations\/MaterialLocalizationMr\/remainingTextFieldCharacterCountOther.html\">remainingTextFieldCharacterCountOther<\/a>, the \"other\" form<\/li>\n<\/ul>",
            "example": "<h2><span>Implementation<\/span><\/h2>\n          <pre class=\"language-dart\"><code class=\"language-dart\">@override\nString get remainingTextFieldCharacterCountZero =&gt; r'\u0915\u094b\u0923\u0924\u0947\u0939\u0940 \u0935\u0930\u094d\u0923 \u0936\u093f\u0932\u094d\u0932\u0915 \u0928\u093e\u0939\u0940\u0924';<\/code><\/pre>\n        ",
            "href": "flutter_localizations\/MaterialLocalizationMr\/remainingTextFieldCharacterCountZero.html",
            "isDeprecated": "0",
            "type": "dart:core.String",
            "memberOf": "flutter_localizations.MaterialLocalizationMr",
            "params": []
        },
        {
            "desc": "<p>The semantics label used for <a href=\"material\/ReorderableListView-class.html\">ReorderableListView<\/a> to reorder an item in the\nlist one space down the list.<\/p>\n        ",
            "example": "<h2><span>Implementation<\/span><\/h2>\n          <pre class=\"language-dart\"><code class=\"language-dart\">@override\nString get reorderItemDown =&gt; r'\u0916\u093e\u0932\u0940 \u0939\u0932\u0935\u093e';<\/code><\/pre>\n        ",
            "href": "flutter_localizations\/MaterialLocalizationMr\/reorderItemDown.html",
            "isDeprecated": "0",
            "type": "dart:core.String",
            "memberOf": "flutter_localizations.MaterialLocalizationMr",
            "params": []
        },
        {
            "desc": "<p>The semantics label used for <a href=\"material\/ReorderableListView-class.html\">ReorderableListView<\/a> to reorder an item in the\nlist one space left in the list.<\/p>\n        ",
            "example": "<h2><span>Implementation<\/span><\/h2>\n          <pre class=\"language-dart\"><code class=\"language-dart\">@override\nString get reorderItemLeft =&gt; r'\u0921\u093e\u0935\u0940\u0915\u0921\u0947 \u0939\u0932\u0935\u093e';<\/code><\/pre>\n        ",
            "href": "flutter_localizations\/MaterialLocalizationMr\/reorderItemLeft.html",
            "isDeprecated": "0",
            "type": "dart:core.String",
            "memberOf": "flutter_localizations.MaterialLocalizationMr",
            "params": []
        },
        {
            "desc": "<p>The semantics label used for <a href=\"material\/ReorderableListView-class.html\">ReorderableListView<\/a> to reorder an item in the\nlist one space right in the list.<\/p>\n        ",
            "example": "<h2><span>Implementation<\/span><\/h2>\n          <pre class=\"language-dart\"><code class=\"language-dart\">@override\nString get reorderItemRight =&gt; r'\u0909\u091c\u0935\u0940\u0915\u0921\u0947 \u0939\u0932\u0935\u093e';<\/code><\/pre>\n        ",
            "href": "flutter_localizations\/MaterialLocalizationMr\/reorderItemRight.html",
            "isDeprecated": "0",
            "type": "dart:core.String",
            "memberOf": "flutter_localizations.MaterialLocalizationMr",
            "params": []
        },
        {
            "desc": "<p>The semantics label used for <a href=\"material\/ReorderableListView-class.html\">ReorderableListView<\/a> to reorder an item in the\nlist to the end of the list.<\/p>\n        ",
            "example": "<h2><span>Implementation<\/span><\/h2>\n          <pre class=\"language-dart\"><code class=\"language-dart\">@override\nString get reorderItemToEnd =&gt; r'\u0936\u0947\u0935\u091f\u093e\u0915\u0921\u0947 \u0939\u0932\u0935\u093e';<\/code><\/pre>\n        ",
            "href": "flutter_localizations\/MaterialLocalizationMr\/reorderItemToEnd.html",
            "isDeprecated": "0",
            "type": "dart:core.String",
            "memberOf": "flutter_localizations.MaterialLocalizationMr",
            "params": []
        },
        {
            "desc": "<p>The semantics label used for <a href=\"material\/ReorderableListView-class.html\">ReorderableListView<\/a> to reorder an item in the\nlist to the start of the list.<\/p>\n        ",
            "example": "<h2><span>Implementation<\/span><\/h2>\n          <pre class=\"language-dart\"><code class=\"language-dart\">@override\nString get reorderItemToStart =&gt; r'\u0938\u0941\u0930\u0941\u0935\u093e\u0924\u0940\u0932\u093e \u0939\u0932\u0935\u093e';<\/code><\/pre>\n        ",
            "href": "flutter_localizations\/MaterialLocalizationMr\/reorderItemToStart.html",
            "isDeprecated": "0",
            "type": "dart:core.String",
            "memberOf": "flutter_localizations.MaterialLocalizationMr",
            "params": []
        },
        {
            "desc": "<p>The semantics label used for <a href=\"material\/ReorderableListView-class.html\">ReorderableListView<\/a> to reorder an item in the\nlist one space up the list.<\/p>\n        ",
            "example": "<h2><span>Implementation<\/span><\/h2>\n          <pre class=\"language-dart\"><code class=\"language-dart\">@override\nString get reorderItemUp =&gt; r'\u0935\u0930 \u0939\u0932\u0935\u093e';<\/code><\/pre>\n        ",
            "href": "flutter_localizations\/MaterialLocalizationMr\/reorderItemUp.html",
            "isDeprecated": "0",
            "type": "dart:core.String",
            "memberOf": "flutter_localizations.MaterialLocalizationMr",
            "params": []
        },
        {
            "desc": "<p>Title for the <a href=\"material\/PaginatedDataTable-class.html\">PaginatedDataTable<\/a>'s \"rows per page\" footer.<\/p>\n        ",
            "example": "<h2><span>Implementation<\/span><\/h2>\n          <pre class=\"language-dart\"><code class=\"language-dart\">@override\nString get rowsPerPageTitle =&gt; r'\u092a\u094d\u0930\u0924\u093f \u092a\u0947\u091c \u092a\u0902\u0915\u094d\u0924\u0940:';<\/code><\/pre>\n        ",
            "href": "flutter_localizations\/MaterialLocalizationMr\/rowsPerPageTitle.html",
            "isDeprecated": "0",
            "type": "dart:core.String",
            "memberOf": "flutter_localizations.MaterialLocalizationMr",
            "params": []
        },
        {
            "desc": "<p>Defines the localized <a href=\"painting\/TextStyle-class.html\">TextStyle<\/a> geometry for <a href=\"material\/ThemeData\/textTheme.html\">ThemeData.textTheme<\/a>.<\/p>\n<p>The <a href=\"flutter_localizations\/MaterialLocalizationMr\/scriptCategory.html\">scriptCategory<\/a> defines the overall geometry of a <a href=\"material\/TextTheme-class.html\">TextTheme<\/a> for\nthe static <code>MaterialTextGeometry.localizedFor<\/code> method in terms of the\nthree language categories defined in <a href=\"https:\/\/material.io\/go\/design-typography\">https:\/\/material.io\/go\/design-typography<\/a>.<\/p>\n<p>Generally speaking, font sizes for <a href=\"material\/ScriptCategory-class.html\">ScriptCategory.tall<\/a> and\n<a href=\"material\/ScriptCategory-class.html\">ScriptCategory.dense<\/a> scripts - for text styles that are smaller than the\ntitle style - are one unit larger than they are for\n<a href=\"material\/ScriptCategory-class.html\">ScriptCategory.englishLike<\/a> scripts.<\/p>\n        ",
            "example": "<h2><span>Implementation<\/span><\/h2>\n          <pre class=\"language-dart\"><code class=\"language-dart\">@override\nScriptCategory get scriptCategory =&gt; ScriptCategory.dense;<\/code><\/pre>\n        ",
            "href": "flutter_localizations\/MaterialLocalizationMr\/scriptCategory.html",
            "isDeprecated": "0",
            "type": "material.ScriptCategory",
            "memberOf": "flutter_localizations.MaterialLocalizationMr",
            "params": []
        },
        {
            "desc": "<p>Label indicating that a text field is a search field. This will be used\nas a hint text in the text field.<\/p>\n        ",
            "example": "<h2><span>Implementation<\/span><\/h2>\n          <pre class=\"language-dart\"><code class=\"language-dart\">@override\nString get searchFieldLabel =&gt; r'\u0936\u094b\u0927';<\/code><\/pre>\n        ",
            "href": "flutter_localizations\/MaterialLocalizationMr\/searchFieldLabel.html",
            "isDeprecated": "0",
            "type": "dart:core.String",
            "memberOf": "flutter_localizations.MaterialLocalizationMr",
            "params": []
        },
        {
            "desc": "<p>Label for \"select all\" edit buttons and menu items.<\/p>\n        ",
            "example": "<h2><span>Implementation<\/span><\/h2>\n          <pre class=\"language-dart\"><code class=\"language-dart\">@override\nString get selectAllButtonLabel =&gt; r'\u0938\u0930\u094d\u0935 \u0928\u093f\u0935\u0921\u093e';<\/code><\/pre>\n        ",
            "href": "flutter_localizations\/MaterialLocalizationMr\/selectAllButtonLabel.html",
            "isDeprecated": "0",
            "type": "dart:core.String",
            "memberOf": "flutter_localizations.MaterialLocalizationMr",
            "params": []
        },
        {
            "desc": "<p>The \"few\" form of <a href=\"flutter_localizations\/GlobalMaterialLocalizations\/selectedRowCountTitle.html\">selectedRowCountTitle<\/a>.<\/p>\n<p>This form is optional.<\/p>\n<p>See also:<\/p>\n<ul>\n<li>\n<a href=\"intl\/Intl\/plural.html\">Intl.plural<\/a>, to which this form is passed.<\/li>\n<li>\n<a href=\"flutter_localizations\/MaterialLocalizationMr\/selectedRowCountTitleZero.html\">selectedRowCountTitleZero<\/a>, the \"zero\" form<\/li>\n<li>\n<a href=\"flutter_localizations\/MaterialLocalizationMr\/selectedRowCountTitleOne.html\">selectedRowCountTitleOne<\/a>, the \"one\" form<\/li>\n<li>\n<a href=\"flutter_localizations\/MaterialLocalizationMr\/selectedRowCountTitleTwo.html\">selectedRowCountTitleTwo<\/a>, the \"two\" form<\/li>\n<li>\n<a href=\"flutter_localizations\/MaterialLocalizationMr\/selectedRowCountTitleMany.html\">selectedRowCountTitleMany<\/a>, the \"many\" form<\/li>\n<li>\n<a href=\"flutter_localizations\/MaterialLocalizationMr\/selectedRowCountTitleOther.html\">selectedRowCountTitleOther<\/a>, the \"other\" form<\/li>\n<\/ul>",
            "example": "<h2><span>Implementation<\/span><\/h2>\n          <pre class=\"language-dart\"><code class=\"language-dart\">@override\nString get selectedRowCountTitleFew =&gt; null;<\/code><\/pre>\n        ",
            "href": "flutter_localizations\/MaterialLocalizationMr\/selectedRowCountTitleFew.html",
            "isDeprecated": "0",
            "type": "dart:core.String",
            "memberOf": "flutter_localizations.MaterialLocalizationMr",
            "params": []
        },
        {
            "desc": "<p>The \"many\" form of <a href=\"flutter_localizations\/GlobalMaterialLocalizations\/selectedRowCountTitle.html\">selectedRowCountTitle<\/a>.<\/p>\n<p>This form is optional.<\/p>\n<p>See also:<\/p>\n<ul>\n<li>\n<a href=\"intl\/Intl\/plural.html\">Intl.plural<\/a>, to which this form is passed.<\/li>\n<li>\n<a href=\"flutter_localizations\/MaterialLocalizationMr\/selectedRowCountTitleZero.html\">selectedRowCountTitleZero<\/a>, the \"zero\" form<\/li>\n<li>\n<a href=\"flutter_localizations\/MaterialLocalizationMr\/selectedRowCountTitleOne.html\">selectedRowCountTitleOne<\/a>, the \"one\" form<\/li>\n<li>\n<a href=\"flutter_localizations\/MaterialLocalizationMr\/selectedRowCountTitleTwo.html\">selectedRowCountTitleTwo<\/a>, the \"two\" form<\/li>\n<li>\n<a href=\"flutter_localizations\/MaterialLocalizationMr\/selectedRowCountTitleFew.html\">selectedRowCountTitleFew<\/a>, the \"few\" form<\/li>\n<li>\n<a href=\"flutter_localizations\/MaterialLocalizationMr\/selectedRowCountTitleOther.html\">selectedRowCountTitleOther<\/a>, the \"other\" form<\/li>\n<\/ul>",
            "example": "<h2><span>Implementation<\/span><\/h2>\n          <pre class=\"language-dart\"><code class=\"language-dart\">@override\nString get selectedRowCountTitleMany =&gt; null;<\/code><\/pre>\n        ",
            "href": "flutter_localizations\/MaterialLocalizationMr\/selectedRowCountTitleMany.html",
            "isDeprecated": "0",
            "type": "dart:core.String",
            "memberOf": "flutter_localizations.MaterialLocalizationMr",
            "params": []
        },
        {
            "desc": "<p>The \"one\" form of <a href=\"flutter_localizations\/GlobalMaterialLocalizations\/selectedRowCountTitle.html\">selectedRowCountTitle<\/a>.<\/p>\n<p>This form is optional.<\/p>\n<p>See also:<\/p>\n<ul>\n<li>\n<a href=\"intl\/Intl\/plural.html\">Intl.plural<\/a>, to which this form is passed.<\/li>\n<li>\n<a href=\"flutter_localizations\/MaterialLocalizationMr\/selectedRowCountTitleZero.html\">selectedRowCountTitleZero<\/a>, the \"zero\" form<\/li>\n<li>\n<a href=\"flutter_localizations\/MaterialLocalizationMr\/selectedRowCountTitleTwo.html\">selectedRowCountTitleTwo<\/a>, the \"two\" form<\/li>\n<li>\n<a href=\"flutter_localizations\/MaterialLocalizationMr\/selectedRowCountTitleFew.html\">selectedRowCountTitleFew<\/a>, the \"few\" form<\/li>\n<li>\n<a href=\"flutter_localizations\/MaterialLocalizationMr\/selectedRowCountTitleMany.html\">selectedRowCountTitleMany<\/a>, the \"many\" form<\/li>\n<li>\n<a href=\"flutter_localizations\/MaterialLocalizationMr\/selectedRowCountTitleOther.html\">selectedRowCountTitleOther<\/a>, the \"other\" form<\/li>\n<\/ul>",
            "example": "<h2><span>Implementation<\/span><\/h2>\n          <pre class=\"language-dart\"><code class=\"language-dart\">@override\nString get selectedRowCountTitleOne =&gt; r'\u090f\u0915 \u0905\u093e\u092f\u091f\u092e \u0928\u093f\u0935\u0921\u0932\u093e';<\/code><\/pre>\n        ",
            "href": "flutter_localizations\/MaterialLocalizationMr\/selectedRowCountTitleOne.html",
            "isDeprecated": "0",
            "type": "dart:core.String",
            "memberOf": "flutter_localizations.MaterialLocalizationMr",
            "params": []
        },
        {
            "desc": "<p>The \"other\" form of <a href=\"flutter_localizations\/GlobalMaterialLocalizations\/selectedRowCountTitle.html\">selectedRowCountTitle<\/a>.<\/p>\n<p>This form is required.<\/p>\n<p>See also:<\/p>\n<ul>\n<li>\n<a href=\"intl\/Intl\/plural.html\">Intl.plural<\/a>, to which this form is passed.<\/li>\n<li>\n<a href=\"flutter_localizations\/MaterialLocalizationMr\/selectedRowCountTitleZero.html\">selectedRowCountTitleZero<\/a>, the \"zero\" form<\/li>\n<li>\n<a href=\"flutter_localizations\/MaterialLocalizationMr\/selectedRowCountTitleOne.html\">selectedRowCountTitleOne<\/a>, the \"one\" form<\/li>\n<li>\n<a href=\"flutter_localizations\/MaterialLocalizationMr\/selectedRowCountTitleTwo.html\">selectedRowCountTitleTwo<\/a>, the \"two\" form<\/li>\n<li>\n<a href=\"flutter_localizations\/MaterialLocalizationMr\/selectedRowCountTitleFew.html\">selectedRowCountTitleFew<\/a>, the \"few\" form<\/li>\n<li>\n<a href=\"flutter_localizations\/MaterialLocalizationMr\/selectedRowCountTitleMany.html\">selectedRowCountTitleMany<\/a>, the \"many\" form<\/li>\n<\/ul>",
            "example": "<h2><span>Implementation<\/span><\/h2>\n          <pre class=\"language-dart\"><code class=\"language-dart\">@override\nString get selectedRowCountTitleOther =&gt; r'$selectedRowCount \u0905\u093e\u092f\u091f\u092e \u0928\u093f\u0935\u0921\u0932\u0947';<\/code><\/pre>\n        ",
            "href": "flutter_localizations\/MaterialLocalizationMr\/selectedRowCountTitleOther.html",
            "isDeprecated": "0",
            "type": "dart:core.String",
            "memberOf": "flutter_localizations.MaterialLocalizationMr",
            "params": []
        },
        {
            "desc": "<p>The \"two\" form of <a href=\"flutter_localizations\/GlobalMaterialLocalizations\/selectedRowCountTitle.html\">selectedRowCountTitle<\/a>.<\/p>\n<p>This form is optional.<\/p>\n<p>See also:<\/p>\n<ul>\n<li>\n<a href=\"intl\/Intl\/plural.html\">Intl.plural<\/a>, to which this form is passed.<\/li>\n<li>\n<a href=\"flutter_localizations\/MaterialLocalizationMr\/selectedRowCountTitleZero.html\">selectedRowCountTitleZero<\/a>, the \"zero\" form<\/li>\n<li>\n<a href=\"flutter_localizations\/MaterialLocalizationMr\/selectedRowCountTitleOne.html\">selectedRowCountTitleOne<\/a>, the \"one\" form<\/li>\n<li>\n<a href=\"flutter_localizations\/MaterialLocalizationMr\/selectedRowCountTitleFew.html\">selectedRowCountTitleFew<\/a>, the \"few\" form<\/li>\n<li>\n<a href=\"flutter_localizations\/MaterialLocalizationMr\/selectedRowCountTitleMany.html\">selectedRowCountTitleMany<\/a>, the \"many\" form<\/li>\n<li>\n<a href=\"flutter_localizations\/MaterialLocalizationMr\/selectedRowCountTitleOther.html\">selectedRowCountTitleOther<\/a>, the \"other\" form<\/li>\n<\/ul>",
            "example": "<h2><span>Implementation<\/span><\/h2>\n          <pre class=\"language-dart\"><code class=\"language-dart\">@override\nString get selectedRowCountTitleTwo =&gt; null;<\/code><\/pre>\n        ",
            "href": "flutter_localizations\/MaterialLocalizationMr\/selectedRowCountTitleTwo.html",
            "isDeprecated": "0",
            "type": "dart:core.String",
            "memberOf": "flutter_localizations.MaterialLocalizationMr",
            "params": []
        },
        {
            "desc": "<p>The \"zero\" form of <a href=\"flutter_localizations\/GlobalMaterialLocalizations\/selectedRowCountTitle.html\">selectedRowCountTitle<\/a>.<\/p>\n<p>This form is optional.<\/p>\n<p>See also:<\/p>\n<ul>\n<li>\n<a href=\"intl\/Intl\/plural.html\">Intl.plural<\/a>, to which this form is passed.<\/li>\n<li>\n<a href=\"flutter_localizations\/MaterialLocalizationMr\/selectedRowCountTitleOne.html\">selectedRowCountTitleOne<\/a>, the \"one\" form<\/li>\n<li>\n<a href=\"flutter_localizations\/MaterialLocalizationMr\/selectedRowCountTitleTwo.html\">selectedRowCountTitleTwo<\/a>, the \"two\" form<\/li>\n<li>\n<a href=\"flutter_localizations\/MaterialLocalizationMr\/selectedRowCountTitleFew.html\">selectedRowCountTitleFew<\/a>, the \"few\" form<\/li>\n<li>\n<a href=\"flutter_localizations\/MaterialLocalizationMr\/selectedRowCountTitleMany.html\">selectedRowCountTitleMany<\/a>, the \"many\" form<\/li>\n<li>\n<a href=\"flutter_localizations\/MaterialLocalizationMr\/selectedRowCountTitleOther.html\">selectedRowCountTitleOther<\/a>, the \"other\" form<\/li>\n<\/ul>",
            "example": "<h2><span>Implementation<\/span><\/h2>\n          <pre class=\"language-dart\"><code class=\"language-dart\">@override\nString get selectedRowCountTitleZero =&gt; r'\u0915\u094b\u0923\u0924\u0947\u0939\u0940 \u0906\u092f\u091f\u092e \u0928\u093f\u0935\u0921\u0932\u0947\u0932\u0947 \u0928\u093e\u0939\u0940\u0924';<\/code><\/pre>\n        ",
            "href": "flutter_localizations\/MaterialLocalizationMr\/selectedRowCountTitleZero.html",
            "isDeprecated": "0",
            "type": "dart:core.String",
            "memberOf": "flutter_localizations.MaterialLocalizationMr",
            "params": []
        },
        {
            "desc": "<p>The semantics label used for the button on <a href=\"material\/UserAccountsDrawerHeader-class.html\">UserAccountsDrawerHeader<\/a> that\nshows the list of accounts.<\/p>\n        ",
            "example": "<h2><span>Implementation<\/span><\/h2>\n          <pre class=\"language-dart\"><code class=\"language-dart\">@override\nString get showAccountsLabel =&gt; r'\u0916\u093e\u0924\u0940 \u0926\u0930\u094d\u0936\u0935\u093e';<\/code><\/pre>\n        ",
            "href": "flutter_localizations\/MaterialLocalizationMr\/showAccountsLabel.html",
            "isDeprecated": "0",
            "type": "dart:core.String",
            "memberOf": "flutter_localizations.MaterialLocalizationMr",
            "params": []
        },
        {
            "desc": "<p>The default <a href=\"material\/PopupMenuButton-class.html\">PopupMenuButton<\/a> tooltip.<\/p>\n        ",
            "example": "<h2><span>Implementation<\/span><\/h2>\n          <pre class=\"language-dart\"><code class=\"language-dart\">@override\nString get showMenuTooltip =&gt; r'\u092e\u0947\u0928\u0942 \u0926\u093e\u0916\u0935\u093e';<\/code><\/pre>\n        ",
            "href": "flutter_localizations\/MaterialLocalizationMr\/showMenuTooltip.html",
            "isDeprecated": "0",
            "type": "dart:core.String",
            "memberOf": "flutter_localizations.MaterialLocalizationMr",
            "params": []
        },
        {
            "desc": "<p>The semantics label used to indicate which account is signed in in the\n<a href=\"material\/UserAccountsDrawerHeader-class.html\">UserAccountsDrawerHeader<\/a> widget.<\/p>\n        ",
            "example": "<h2><span>Implementation<\/span><\/h2>\n          <pre class=\"language-dart\"><code class=\"language-dart\">@override\nString get signedInLabel =&gt; r'\u0938\u093e\u0907\u0928 \u0907\u0928 \u0915\u0947\u0932\u0947 \u0906\u0939\u0947';<\/code><\/pre>\n        ",
            "href": "flutter_localizations\/MaterialLocalizationMr\/signedInLabel.html",
            "isDeprecated": "0",
            "type": "dart:core.String",
            "memberOf": "flutter_localizations.MaterialLocalizationMr",
            "params": []
        },
        {
            "desc": "<p>The raw version of <a href=\"flutter_localizations\/GlobalMaterialLocalizations\/tabLabel.html\">tabLabel<\/a>, with <code>$tabIndex<\/code> and <code>$tabCount<\/code> verbatim\nin the string.<\/p>\n        ",
            "example": "<h2><span>Implementation<\/span><\/h2>\n          <pre class=\"language-dart\"><code class=\"language-dart\">@override\nString get tabLabelRaw =&gt; r'$tabCount \u092a\u0948\u0915\u0940 $tabIndex \u091f\u0945\u092c';<\/code><\/pre>\n        ",
            "href": "flutter_localizations\/MaterialLocalizationMr\/tabLabelRaw.html",
            "isDeprecated": "0",
            "type": "dart:core.String",
            "memberOf": "flutter_localizations.MaterialLocalizationMr",
            "params": []
        },
        {
            "desc": "<p>The format to use for <a href=\"flutter_localizations\/GlobalMaterialLocalizations\/timeOfDayFormat.html\">timeOfDayFormat<\/a>.<\/p>\n        ",
            "example": "<h2><span>Implementation<\/span><\/h2>\n          <pre class=\"language-dart\"><code class=\"language-dart\">@override\nTimeOfDayFormat get timeOfDayFormatRaw =&gt; TimeOfDayFormat.h_colon_mm_space_a;<\/code><\/pre>\n        ",
            "href": "flutter_localizations\/MaterialLocalizationMr\/timeOfDayFormatRaw.html",
            "isDeprecated": "0",
            "type": "material.TimeOfDayFormat",
            "memberOf": "flutter_localizations.MaterialLocalizationMr",
            "params": []
        },
        {
            "desc": "<p>The text-to-speech announcement made when a time picker invoked using\n<a href=\"material\/showTimePicker.html\">showTimePicker<\/a> is set to the hour picker mode.<\/p>\n        ",
            "example": "<h2><span>Implementation<\/span><\/h2>\n          <pre class=\"language-dart\"><code class=\"language-dart\">@override\nString get timePickerHourModeAnnouncement =&gt; r'\u0924\u093e\u0938 \u0928\u093f\u0935\u0921\u093e';<\/code><\/pre>\n        ",
            "href": "flutter_localizations\/MaterialLocalizationMr\/timePickerHourModeAnnouncement.html",
            "isDeprecated": "0",
            "type": "dart:core.String",
            "memberOf": "flutter_localizations.MaterialLocalizationMr",
            "params": []
        },
        {
            "desc": "<p>The text-to-speech announcement made when a time picker invoked using\n<a href=\"material\/showTimePicker.html\">showTimePicker<\/a> is set to the minute picker mode.<\/p>\n        ",
            "example": "<h2><span>Implementation<\/span><\/h2>\n          <pre class=\"language-dart\"><code class=\"language-dart\">@override\nString get timePickerMinuteModeAnnouncement =&gt; r'\u092e\u093f\u0928\u093f\u091f\u0947 \u0928\u093f\u0935\u0921\u093e';<\/code><\/pre>\n        ",
            "href": "flutter_localizations\/MaterialLocalizationMr\/timePickerMinuteModeAnnouncement.html",
            "isDeprecated": "0",
            "type": "dart:core.String",
            "memberOf": "flutter_localizations.MaterialLocalizationMr",
            "params": []
        },
        {
            "desc": "<p>Label for the <a href=\"material\/AboutDialog-class.html\">AboutDialog<\/a> button that shows the <a href=\"material\/LicensePage-class.html\">LicensePage<\/a>.<\/p>\n        ",
            "example": "<h2><span>Implementation<\/span><\/h2>\n          <pre class=\"language-dart\"><code class=\"language-dart\">@override\nString get viewLicensesButtonLabel =&gt; r'\u092a\u0930\u0935\u093e\u0928\u0947 \u092a\u093e\u0939\u093e';<\/code><\/pre>\n        ",
            "href": "flutter_localizations\/MaterialLocalizationMr\/viewLicensesButtonLabel.html",
            "isDeprecated": "0",
            "type": "dart:core.String",
            "memberOf": "flutter_localizations.MaterialLocalizationMr",
            "params": []
        }
    ]
}