{
    "name": "material.DataColumn",
    "extends": [],
    "memberOf": "material",
    "events": [
        {
            "name": "onSort",
            "type": "material.DataColumnSortCallback",
            "desc": "<p>Called when the user asks to sort the table using this column.<\/p>\n<p>If null, the column will not be considered sortable.<\/p>\n<p>See <a href=\"material\/DataTable\/sortColumnIndex.html\">DataTable.sortColumnIndex<\/a> and <a href=\"material\/DataTable\/sortAscending.html\">DataTable.sortAscending<\/a>.<\/p>\n        ",
            "static": false,
            "memberOf": "",
            "sig": "",
            "params": [],
            "isConstructor": false,
            "href": "material\/DataColumn\/onSort.html",
            "example": "<h2><span>Implementation<\/span><\/h2>\n          <pre class=\"language-dart\"><code class=\"language-dart\">final DataColumnSortCallback onSort\n\n<\/code><\/pre>\n        ",
            "isDeprecated": false,
            "isConstant": false
        }
    ],
    "methods": [
        {
            "name": "DataColumn",
            "type": "",
            "desc": "<p>Creates the configuration for a column of a <a href=\"material\/DataTable-class.html\">DataTable<\/a>.<\/p>\n<p>The <code>label<\/code> argument must not be null.<\/p>\n    ",
            "static": false,
            "memberOf": "material.DataColumn",
            "sig": "",
            "params": [
                {
                    "name": "label",
                    "type": "widgets.Widget",
                    "desc": "",
                    "isOptional": true,
                    "href": "",
                    "example": "",
                    "isDeprecated": false
                },
                {
                    "name": "tooltip",
                    "type": "dart:core.String",
                    "desc": "",
                    "isOptional": true,
                    "href": "",
                    "example": "",
                    "isDeprecated": false
                },
                {
                    "name": "numeric",
                    "type": "dart:core.bool",
                    "desc": "",
                    "isOptional": true,
                    "href": "",
                    "example": "",
                    "isDeprecated": false
                },
                {
                    "name": "onSort",
                    "type": "material.DataColumnSortCallback",
                    "desc": "",
                    "isOptional": true,
                    "href": "",
                    "example": "",
                    "isDeprecated": false
                }
            ],
            "isConstructor": true,
            "href": "material\/DataColumn\/DataColumn.html",
            "example": "<h2><span>Implementation<\/span><\/h2>\n      <pre class=\"language-dart\"><code class=\"language-dart\">const DataColumn({\n  @required this.label,\n  this.tooltip,\n  this.numeric = false,\n  this.onSort,\n}) : assert(label != null);<\/code><\/pre>\n    ",
            "isDeprecated": false
        }
    ],
    "props": [
        {
            "name": "label",
            "type": "widgets.Widget",
            "types": [],
            "desc": "<p>The column heading.<\/p>\n<p>Typically, this will be a <a href=\"widgets\/Text-class.html\">Text<\/a> widget. It could also be an\n<a href=\"widgets\/Icon-class.html\">Icon<\/a> (typically using size 18), or a <a href=\"widgets\/Row-class.html\">Row<\/a> with an icon and\nsome text.<\/p>\n<p>The label should not include the sort indicator.<\/p>\n        ",
            "memberOf": "material.DataColumn",
            "isConstant": false,
            "href": "material\/DataColumn\/label.html",
            "example": "<h2><span>Implementation<\/span><\/h2>\n          <pre class=\"language-dart\"><code class=\"language-dart\">final Widget label\n\n<\/code><\/pre>\n        ",
            "isDeprecated": false
        },
        {
            "name": "numeric",
            "type": "dart:core.bool",
            "types": [],
            "desc": "<p>Whether this column represents numeric data or not.<\/p>\n<p>The contents of cells of columns containing numeric data are\nright-aligned.<\/p>\n        ",
            "memberOf": "material.DataColumn",
            "isConstant": false,
            "href": "material\/DataColumn\/numeric.html",
            "example": "<h2><span>Implementation<\/span><\/h2>\n          <pre class=\"language-dart\"><code class=\"language-dart\">final bool numeric\n\n<\/code><\/pre>\n        ",
            "isDeprecated": false
        },
        {
            "name": "tooltip",
            "type": "dart:core.String",
            "types": [],
            "desc": "<p>The column heading's tooltip.<\/p>\n<p>This is a longer description of the column heading, for cases\nwhere the heading might have been abbreviated to keep the column\nwidth to a reasonable size.<\/p>\n        ",
            "memberOf": "material.DataColumn",
            "isConstant": false,
            "href": "material\/DataColumn\/tooltip.html",
            "example": "<h2><span>Implementation<\/span><\/h2>\n          <pre class=\"language-dart\"><code class=\"language-dart\">final String tooltip\n\n<\/code><\/pre>\n        ",
            "isDeprecated": false
        }
    ],
    "isMixin": false,
    "isEnum": false,
    "isTypedef": false,
    "isConstant": false,
    "isAbstract": false,
    "implementors": [],
    "realImplementors": [],
    "cn": [],
    "href": "material\/DataColumn-class.html",
    "desc": "<p>Column configuration for a <a href=\"material\/DataTable-class.html\">DataTable<\/a>.<\/p>\n<p>One column configuration must be provided for each column to\ndisplay in the table. The list of <a href=\"material\/DataColumn-class.html\">DataColumn<\/a> objects is passed\nas the <code>columns<\/code> argument to the <a href=\"material\/DataTable\/DataTable.html\">new DataTable<\/a> constructor.<\/p>\n    ",
    "example": "",
    "isDeprecated": false,
    "dtype": "class",
    "shortname": "DataColumn"
}