{
    "desc": "<p>The possible alignments of a <a href=\"material\/Drawer-class.html\">Drawer<\/a>.<\/p>\n    ",
    "dtype": "enum",
    "example": "",
    "href": "material\/DrawerAlignment-class.html",
    "isAbstract": false,
    "isConstant": "0",
    "isDeprecated": false,
    "is_enum": 1,
    "is_mixin": 1,
    "is_typedef": 1,
    "memberOf": "material",
    "name": "material.DrawerAlignment",
    "shortname": "DrawerAlignment",
    "extends": [],
    "realImplementors": [],
    "events": [],
    "methods": [],
    "props": []
}