{
    "type": "",
    "name": "painting.Axis",
    "extends": [],
    "memberOf": "painting",
    "events": [],
    "methods": [
        {
            "name": "toString",
            "type": "dart:core.String",
            "desc": "<p>Returns a string representation of this object.<\/p>\n    ",
            "static": false,
            "memberOf": "painting.Axis",
            "sig": "",
            "params": [],
            "isConstructor": false,
            "href": "painting\/Axis\/toString.html",
            "example": "",
            "isDeprecated": false
        }
    ],
    "props": [],
    "isMixin": false,
    "isEnum": true,
    "isTypedef": false,
    "isConstant": false,
    "isAbstract": false,
    "implementors": [],
    "realImplementors": [],
    "cn": [],
    "href": "painting\/Axis-class.html",
    "desc": "<p>The two cardinal directions in two dimensions.<\/p>\n<p>The axis is always relative to the current coordinate space. This means, for\nexample, that a <a href=\"painting\/Axis-class.html\">horizontal<\/a> axis might actually be diagonally from top\nright to bottom left, due to some local <a href=\"widgets\/Transform-class.html\">Transform<\/a> applied to the scene.<\/p>\n<p>See also:<\/p>\n<ul>\n<li>\n<a href=\"painting\/AxisDirection-class.html\">AxisDirection<\/a>, which is a directional version of this enum (with values\nlight left and right, rather than just horizontal).<\/li>\n<li>\n<a href=\"dart-ui\/TextDirection-class.html\">TextDirection<\/a>, which disambiguates between left-to-right horizontal\ncontent and right-to-left horizontal content.<\/li>\n<\/ul>",
    "example": "",
    "isDeprecated": false,
    "dtype": "enum",
    "shortname": "Axis"
}