{
    "desc": "<p>How to paint any portions of a box not covered by an image.<\/p>\n    ",
    "dtype": "enum",
    "example": "",
    "href": "painting\/ImageRepeat-class.html",
    "isAbstract": false,
    "isConstant": "0",
    "isDeprecated": false,
    "is_enum": 1,
    "is_mixin": 1,
    "is_typedef": 1,
    "memberOf": "painting",
    "name": "painting.ImageRepeat",
    "shortname": "ImageRepeat",
    "extends": [],
    "realImplementors": [],
    "events": [],
    "methods": [],
    "props": []
}