{
    "desc": "<p>Configures how the platform keyboard will select an uppercase or\nlowercase keyboard.<\/p>\n<p>Only supports text keyboards, other keyboard types will ignore this\nconfiguration. Capitalization is locale-aware.<\/p>\n    ",
    "dtype": "enum",
    "example": "",
    "href": "services\/TextCapitalization-class.html",
    "isAbstract": false,
    "isConstant": false,
    "isDeprecated": false,
    "memberOf": "services",
    "name": "services.TextCapitalization",
    "shortname": "TextCapitalization",
    "extends": [],
    "is_enum": true,
    "is_mixin": false,
    "realImplementors": [],
    "events": [],
    "methods": [],
    "props": [
        {
            "desc": "\n          <p>Defaults to an uppercase keyboard for each character.<\/p>\n<p>Corresponds to <code>InputType.TYPE_TEXT_FLAG_CAP_CHARACTERS<\/code> on Android, and\n<code>UITextAutocapitalizationTypeAllCharacters<\/code> on iOS.<\/p>\n                  \n  <div>\n            <span class=\"signature\"><code>const TextCapitalization(2)<\/code><\/span>\n          <\/div>\n        ",
            "example": "",
            "href": "",
            "name": "characters",
            "isDeprecated": false,
            "type": "",
            "dtype": "enum-value",
            "isStatic": true,
            "isConstant": true,
            "memberOf": "services.TextCapitalization",
            "params": []
        },
        {
            "desc": "\n          <p>Defaults to a lowercase keyboard.<\/p>\n                  \n  <div>\n            <span class=\"signature\"><code>const TextCapitalization(3)<\/code><\/span>\n          <\/div>\n        ",
            "example": "",
            "href": "",
            "name": "none",
            "isDeprecated": false,
            "type": "",
            "dtype": "enum-value",
            "isStatic": true,
            "isConstant": true,
            "memberOf": "services.TextCapitalization",
            "params": []
        },
        {
            "desc": "\n          <p>Defaults to an uppercase keyboard for the first letter of each sentence.<\/p>\n<p>Corresponds to <code>InputType.TYPE_TEXT_FLAG_CAP_SENTENCES<\/code> on Android, and\n<code>UITextAutocapitalizationTypeSentences<\/code> on iOS.<\/p>\n                  \n  <div>\n            <span class=\"signature\"><code>const TextCapitalization(1)<\/code><\/span>\n          <\/div>\n        ",
            "example": "",
            "href": "",
            "name": "sentences",
            "isDeprecated": false,
            "type": "",
            "dtype": "enum-value",
            "isStatic": true,
            "isConstant": true,
            "memberOf": "services.TextCapitalization",
            "params": []
        },
        {
            "desc": "\n          <p>A constant List of the values in this enum, in order of their declaration.<\/p>\n                  \n  <div>\n            <span class=\"signature\"><code>const List&lt;<wbr><span class=\"type-parameter\">TextCapitalization<\/span>&gt;<\/wbr><\/code><\/span>\n          <\/div>\n        ",
            "example": "",
            "href": "",
            "name": "values",
            "isDeprecated": false,
            "type": "",
            "dtype": "enum-value",
            "isStatic": true,
            "isConstant": true,
            "memberOf": "services.TextCapitalization",
            "params": []
        },
        {
            "desc": "\n          <p>Defaults to an uppercase keyboard for the first letter of each word.<\/p>\n<p>Corresponds to <code>InputType.TYPE_TEXT_FLAG_CAP_WORDS<\/code> on Android, and\n<code>UITextAutocapitalizationTypeWords<\/code> on iOS.<\/p>\n                  \n  <div>\n            <span class=\"signature\"><code>const TextCapitalization(0)<\/code><\/span>\n          <\/div>\n        ",
            "example": "",
            "href": "",
            "name": "words",
            "isDeprecated": false,
            "type": "",
            "dtype": "enum-value",
            "isStatic": true,
            "isConstant": true,
            "memberOf": "services.TextCapitalization",
            "params": []
        }
    ]
}