{
    "desc": "<p>Specifies which of two children to show. See <a href=\"widgets\/AnimatedCrossFade-class.html\">AnimatedCrossFade<\/a>.<\/p>\n<p>The child that is shown will fade in, while the other will fade out.<\/p>\n    ",
    "dtype": "enum",
    "example": "",
    "href": "widgets\/CrossFadeState-class.html",
    "isAbstract": false,
    "isConstant": "0",
    "isDeprecated": false,
    "memberOf": "widgets",
    "name": "widgets.CrossFadeState",
    "shortname": "CrossFadeState",
    "extends": [],
    "is_enum": true,
    "is_mixin": false,
    "realImplementors": [],
    "events": [],
    "methods": [],
    "props": [
        {
            "desc": "\n          <p>A constant List of the values in this enum, in order of their declaration.<\/p>\n                  \n  <div>\n            <span class=\"signature\"><code>const List&lt;<wbr><span class=\"type-parameter\">CrossFadeState<\/span>&gt;<\/wbr><\/code><\/span>\n          <\/div>\n        ",
            "example": "",
            "href": "",
            "name": "showFirst",
            "isDeprecated": false,
            "type": "",
            "dtype": "enum-value",
            "isStatic": true,
            "isConstant": true,
            "memberOf": "widgets.CrossFadeState",
            "params": []
        }
    ]
}